cprotobuf/__init__.py
cprotobuf/internal.c
cprotobuf/internal.cpython-312-darwin.so
cprotobuf/internal.pyx
cprotobuf/plugin.py
cprotobuf/plugin_pb.py
cprotobuf/utils.pxi
cprotobuf-0.1.12.dist-info/licenses/LICENSE
cprotobuf-0.1.12.dist-info/METADATA
cprotobuf-0.1.12.dist-info/WHEEL
cprotobuf-0.1.12.dist-info/entry_points.txt
cprotobuf-0.1.12.dist-info/top_level.txt
cprotobuf-0.1.12.dist-info/RECORD
