Metadata-Version: 2.4
Name: cprotobuf
Version: 0.1.12
Summary: pythonic and high performance protocol buffer implementation.
Requires-Python: >=3.7
License-File: LICENSE
Dynamic: license-file
